README.md
setup.py
atosflow/__init__.py
atosflow/utils.py
atosflow.egg-info/PKG-INFO
atosflow.egg-info/SOURCES.txt
atosflow.egg-info/dependency_links.txt
atosflow.egg-info/top_level.txt