Metadata-Version: 1.2
Name: atosflow
Version: 0.0.2
Summary: mlops
Home-page: https://atos.net/en/
Author: atos
License: WTFPL
Platform: UNKNOWN
Requires-Python: >=2.7
